autotraino/.gitignore
autotraino/LICENSE
autotraino/README.md
autotraino/__init__.py
autotraino/requirements.txt
autotraino/.idea/workspace.xml
autotraino/gluon/__init__.py
autotraino-0.1.0.dist-info/METADATA
autotraino-0.1.0.dist-info/WHEEL
autotraino-0.1.0.dist-info/licenses/LICENSE
autotraino-0.1.0.dist-info/RECORD
